flow_network/network.py
flow_network/__version__.py
flow_network/edges.py
flow_network/tests.py
flow_network/__init__.py
flow_network/pycore/py_minimum_cost_flow.py
flow_network/pycore/__init__.py
flow_network/core/_core.cpython-39-x86_64-linux-gnu.so
flow_network/core/core.py
flow_network/core/__init__.py
flow_network-0.1.13.dist-info/WHEEL
flow_network-0.1.13.dist-info/top_level.txt
flow_network-0.1.13.dist-info/RECORD
flow_network-0.1.13.dist-info/METADATA
flow_network-0.1.13.dist-info/LICENSE
