Metadata-Version: 2.1
Name: flow-network
Version: 0.1.13
Summary: Flow Network Python Library
Home-page: https://github.com/LucienShui/flow-network
Author: Lucien Shui
Author-email: lucien@lucien.ink
License: UNKNOWN
Platform: UNKNOWN
